google_docstring_2md/__init__.py
google_docstring_2md/__main__.py
google_docstring_2md/config.py
google_docstring_2md/converter.py
google_docstring_2md/docstring_processor.py
google_docstring_2md/document_tree.py
google_docstring_2md/github_linker.py
google_docstring_2md/reference_parser.py
google_docstring_2md/signature_formatter.py
google_docstring_2md/utils.py
google_docstring_2md-0.0.2.dist-info/licenses/LICENSE
google_docstring_2md-0.0.2.dist-info/METADATA
google_docstring_2md-0.0.2.dist-info/WHEEL
google_docstring_2md-0.0.2.dist-info/entry_points.txt
google_docstring_2md-0.0.2.dist-info/top_level.txt
google_docstring_2md-0.0.2.dist-info/RECORD
