Metadata-Version: 2.4
Name: google-docstring-2md
Version: 0.0.2
Summary: A tool to convert Google-style docstrings to markdown format
Author-email: Vladimir Iglovikov <iglovikov@gmail.com>
Maintainer: Vladimir Iglovikov
License: Custom License - See LICENSE file for details
Project-URL: bug tracker, https://github.com/ternaus/google-docstring-2md/issues
Project-URL: homepage, https://github.com/ternaus/google-docstring-2md
Keywords: docstring,documentation,docusaurus,google-style,markdown,parser,python,static-analysis,type-hints
Classifier: Development Status :: 5 - Production/Stable
Classifier: Intended Audience :: Developers
Classifier: Intended Audience :: Science/Research
Classifier: Operating System :: OS Independent
Classifier: Programming Language :: Python
Classifier: Programming Language :: Python :: 3 :: Only
Classifier: Programming Language :: Python :: 3.10
Classifier: Programming Language :: Python :: 3.11
Classifier: Programming Language :: Python :: 3.12
Classifier: Programming Language :: Python :: 3.13
Classifier: Topic :: Scientific/Engineering :: Artificial Intelligence
Classifier: Topic :: Software Development :: Documentation
Classifier: Topic :: Software Development :: Libraries
Classifier: Topic :: Software Development :: Libraries :: Python Modules
Classifier: Typing :: Typed
Requires-Python: >=3.10
License-File: LICENSE
Requires-Dist: docstring-parser>=0.15
Requires-Dist: google-docstring-parser
Requires-Dist: tqdm>=4.65
Provides-Extra: dev
Requires-Dist: pre-commit>=3.5; extra == "dev"
Requires-Dist: pytest>=8.3.3; extra == "dev"
Dynamic: license-file
